nbiatoolkit/__init__.py
nbiatoolkit/auth.py
nbiatoolkit/dicomsort/__init__.py
nbiatoolkit/dicomsort/dicomsort.py
nbiatoolkit/dicomsort/helper_functions.py
nbiatoolkit/dicomtags/__init__.py
nbiatoolkit/dicomtags/tags.py
nbiatoolkit/logger/README.md
nbiatoolkit/logger/__init__.py
nbiatoolkit/logger/logger.py
nbiatoolkit/nbia.py
nbiatoolkit/nbia_cli.py
nbiatoolkit/utils/__init__.py
nbiatoolkit/utils/conv_response_list.py
nbiatoolkit/utils/md5.py
nbiatoolkit/utils/nbia_endpoints.py
nbiatoolkit/utils/parsers.py
nbiatoolkit-1.3.1.dist-info/LICENSE
nbiatoolkit-1.3.1.dist-info/METADATA
nbiatoolkit-1.3.1.dist-info/WHEEL
nbiatoolkit-1.3.1.dist-info/entry_points.txt
nbiatoolkit-1.3.1.dist-info/RECORD
